invenio_app_rdm/__init__.py
invenio_app_rdm/cli.py
invenio_app_rdm/config.py
invenio_app_rdm/ext.py
invenio_app_rdm/tasks.py
invenio_app_rdm/views.py
invenio_app_rdm/administration/__init__.py
invenio_app_rdm/administration/audit_logs/__init__.py
invenio_app_rdm/administration/audit_logs/audit_logs.py
invenio_app_rdm/administration/domains/__init__.py
invenio_app_rdm/administration/domains/domains.py
invenio_app_rdm/administration/records/__init__.py
invenio_app_rdm/administration/records/records.py
invenio_app_rdm/administration/templates/semantic-ui/invenio_app_rdm/administration/audit_logs.html
invenio_app_rdm/administration/templates/semantic-ui/invenio_app_rdm/administration/domains_search.html
invenio_app_rdm/administration/templates/semantic-ui/invenio_app_rdm/administration/user_moderation.html
invenio_app_rdm/administration/templates/semantic-ui/invenio_app_rdm/administration/user_moderation_details.html
invenio_app_rdm/administration/templates/semantic-ui/invenio_app_rdm/administration/users_search.html
invenio_app_rdm/administration/templates/semantic-ui/invenio_app_rdm/administration/records/drafts.html
invenio_app_rdm/administration/templates/semantic-ui/invenio_app_rdm/administration/records/records.html
invenio_app_rdm/administration/user_moderation/__init__.py
invenio_app_rdm/administration/user_moderation/user_moderation.py
invenio_app_rdm/administration/users/__init__.py
invenio_app_rdm/administration/users/users.py
invenio_app_rdm/administration/views/__init__.py
invenio_app_rdm/administration/views/ui.py
invenio_app_rdm/communities_ui/__init__.py
invenio_app_rdm/communities_ui/searchapp.py
invenio_app_rdm/communities_ui/sitemap.py
invenio_app_rdm/communities_ui/templates/semantic-ui/invenio_communities/collections/collection.html
invenio_app_rdm/communities_ui/templates/semantic-ui/invenio_communities/collections/macros.html
invenio_app_rdm/communities_ui/templates/semantic-ui/invenio_communities/details/browse/index.html
invenio_app_rdm-13.0.7.dist-info/licenses/LICENSE
invenio_app_rdm-13.0.7.dist-info/METADATA
invenio_app_rdm-13.0.7.dist-info/WHEEL
invenio_app_rdm-13.0.7.dist-info/entry_points.txt
invenio_app_rdm-13.0.7.dist-info/top_level.txt
invenio_app_rdm-13.0.7.dist-info/RECORD
