Metadata-Version: 2.4
Name: invenio-app-rdm
Version: 13.0.7
Summary: Invenio Research Data Management.
Home-page: https://github.com/inveniosoftware/invenio-app-rdm
Author: CERN
Author-email: info@inveniosoftware.org
License: MIT
Keywords: invenio-app-rdm Invenio
Platform: any
Classifier: Development Status :: 5 - Production/Stable
Requires-Python: >=3.7
License-File: LICENSE
Requires-Dist: invenio-app<3.0.0,>=2.1.0
Requires-Dist: invenio-base<3.0.0,>=2.1.0
Requires-Dist: invenio-cache<3.0.0,>=2.0.0
Requires-Dist: invenio-celery<3.0.0,>=2.0.0
Requires-Dist: invenio-config<2.0.0,>=1.0.3
Requires-Dist: invenio-i18n<4.0.0,>=3.0.0
Requires-Dist: invenio-db[mysql,postgresql]<3.0.0,>=2.0.0
Requires-Dist: invenio-assets<5.0.0,>=4.0.0
Requires-Dist: invenio-formatter<4.0.0,>=3.0.0
Requires-Dist: invenio-logging<5.0.0,>=4.0.0
Requires-Dist: invenio-mail<3.0.0,>=2.0.0
Requires-Dist: invenio-rest<3.0.0,>=2.0.0
Requires-Dist: invenio-theme<5.0.0,>=4.0.0
Requires-Dist: invenio-access<5.0.0,>=4.0.0
Requires-Dist: invenio-accounts<7.0.0,>=6.0.0
Requires-Dist: invenio-oauth2server<4.0.0,>=3.0.0
Requires-Dist: invenio-oauthclient<6.0.0,>=5.0.0
Requires-Dist: invenio-userprofiles<5.0.0,>=4.0.0
Requires-Dist: invenio-indexer<4.0.0,>=3.0.0
Requires-Dist: invenio-jsonschemas<3.0.0,>=2.0.0
Requires-Dist: invenio-oaiserver<4.0.0,>=3.0.0
Requires-Dist: invenio-pidstore<3.0.0,>=2.0.0
Requires-Dist: invenio-records-rest<4.0.0,>=3.0.0
Requires-Dist: invenio-records-ui<3.0.0,>=2.0.0
Requires-Dist: invenio-records<4.0.0,>=3.0.0
Requires-Dist: invenio-search-ui<5.0.0,>=4.0.0
Requires-Dist: invenio-files-rest<4.0.0,>=3.0.0
Requires-Dist: invenio-previewer<4.0.0,>=3.0.0
Requires-Dist: invenio-records-files<2.0.0,>=1.2.1
Requires-Dist: invenio-collections<1.0.0,>=0.4.0
Requires-Dist: invenio-communities<20.0.0,>=19.0.0
Requires-Dist: invenio-rdm-records<20.0.0,>=19.0.0
Requires-Dist: CairoSVG<3.0.0,>=2.5.2
Requires-Dist: invenio-banners<6.0.0,>=5.0.0
Requires-Dist: invenio-pages<8.0.0,>=7.0.0
Requires-Dist: invenio-audit-logs<1.0.0,>=0.1.0
Requires-Dist: invenio-sitemap<2.0.0,>=0.1.0
Provides-Extra: tests
Requires-Dist: pytest-black-ng>=0.4.0; extra == "tests"
Requires-Dist: pytest-invenio<4.0.0,>=3.3.0; extra == "tests"
Requires-Dist: Sphinx>=4.5.0; extra == "tests"
Requires-Dist: time-machine<3.0.0,>=2.12.0; extra == "tests"
Provides-Extra: elasticsearch7
Requires-Dist: invenio-search[elasticsearch7]<4.0.0,>=3.0.0; extra == "elasticsearch7"
Provides-Extra: opensearch1
Requires-Dist: invenio-search[opensearch1]<4.0.0,>=3.0.0; extra == "opensearch1"
Provides-Extra: opensearch2
Requires-Dist: invenio-search[opensearch2]<4.0.0,>=3.0.0; extra == "opensearch2"
Provides-Extra: s3
Requires-Dist: invenio-s3<4.0.0,>=3.0.0; extra == "s3"
Dynamic: license-file
